sqliteworks.py
sqliteworks-0.1.0.dist-info/LICENSE
sqliteworks-0.1.0.dist-info/METADATA
sqliteworks-0.1.0.dist-info/WHEEL
sqliteworks-0.1.0.dist-info/top_level.txt
sqliteworks-0.1.0.dist-info/RECORD
